Metadata-Version: 2.1
Name: lyydatapolars
Version: 1.2
Summary: lyydatapolars
Author: lyy
Author-email: 
License: MIT
License-File: LICENSE
